boonamber/__init__.py
boonamber/util/ambererror.py
boonamber/util/convert.py
boonamber/v1/__init__.py
boonamber/v2/__init__.py
boonamber/v2/amber_client.py
boonamber/v2/api_client.py
boonamber/v2/configuration.py
boonamber/v2/rest.py
boonamber/v2/api/__init__.py
boonamber/v2/api/default_api.py
boonamber/v2/models/__init__.py
boonamber/v2/models/amber_state.py
boonamber/v2/models/analytic_results.py
boonamber/v2/models/autotune_config.py
boonamber/v2/models/config_response.py
boonamber/v2/models/data_set_run_response.py
boonamber/v2/models/delete_model_response.py
boonamber/v2/models/error.py
boonamber/v2/models/feature_config.py
boonamber/v2/models/feature_config_response.py
boonamber/v2/models/feature_root_cause.py
boonamber/v2/models/fusion_feature.py
boonamber/v2/models/get_model_data_set_run_response.py
boonamber/v2/models/get_models_response.py
boonamber/v2/models/get_nano_status_response.py
boonamber/v2/models/get_pretrain_response.py
boonamber/v2/models/get_root_cause_response.py
boonamber/v2/models/get_status_response.py
boonamber/v2/models/get_summary_response.py
boonamber/v2/models/get_version_response.py
boonamber/v2/models/m_amber_status.py
boonamber/v2/models/m_autotune.py
boonamber/v2/models/m_buffer_stats.py
boonamber/v2/models/m_nano.py
boonamber/v2/models/m_nano_backend.py
boonamber/v2/models/m_nano_config.py
boonamber/v2/models/m_pattern_memory.py
boonamber/v2/models/m_recent_ams.py
boonamber/v2/models/m_recent_analytics.py
boonamber/v2/models/m_recent_floats.py
boonamber/v2/models/m_recent_ids.py
boonamber/v2/models/m_recent_samples.py
boonamber/v2/models/m_recent_times.py
boonamber/v2/models/m_streaming_parameters.py
boonamber/v2/models/m_training.py
boonamber/v2/models/magic_number.py
boonamber/v2/models/map.py
boonamber/v2/models/mncp.py
boonamber/v2/models/model.py
boonamber/v2/models/model_status.py
boonamber/v2/models/nano_status.py
boonamber/v2/models/percent_variation.py
boonamber/v2/models/post_config_request.py
boonamber-2.0.18.dist-info/LICENSE
boonamber-2.0.18.dist-info/METADATA
boonamber-2.0.18.dist-info/WHEEL
boonamber-2.0.18.dist-info/top_level.txt
boonamber-2.0.18.dist-info/RECORD
