Metadata-Version: 2.2
Name: boonamber
Version: 2.0.18
Summary: An SDK for Boon Amber sensor analytics
Author: BoonLogic
Author-email: amber-support@boonlogic.com
License: MIT
Project-URL: repository, https://github.com/boonlogic/amber-python-sdk
Classifier: License :: OSI Approved :: MIT License
Classifier: Programming Language :: Python :: 3
Classifier: Operating System :: OS Independent
License-File: LICENSE
Requires-Dist: requests
Requires-Dist: numpy
